{
  "unversionedId": "IDENTT",
  "id": "IDENTT",
  "isDocsHomePage": false,
  "title": "IDENTT",
  "description": "Coming Soon...",
  "source": "@site/docs/IDENTT.md",
  "slug": "/IDENTT",
  "permalink": "/IDENTT",
  "editUrl": "https://github.com/IDEP-network/IDEP-Docs/docs/IDENTT.md",
  "version": "current",
  "sidebar": "docs",
  "previous": {
    "title": "Senary App",
    "permalink": "/SenaryApp"
  },
  "next": {
    "title": "Client Introduction",
    "permalink": "/Client/Introduction"
  }
}