{
  "unversionedId": "KnowledgeBase/license",
  "id": "KnowledgeBase/license",
  "title": "License",
  "description": "License",
  "source": "@site/docs/KnowledgeBase/license.md",
  "sourceDirName": "KnowledgeBase",
  "slug": "/KnowledgeBase/license",
  "permalink": "/docs/KnowledgeBase/license",
  "editUrl": "https://github.com/facebook/docusaurus/tree/main/packages/create-docusaurus/templates/shared/docs/KnowledgeBase/license.md",
  "tags": [],
  "version": "current",
  "frontMatter": {
    "title": "License"
  },
  "sidebar": "Docs",
  "previous": {
    "title": "Branding Guide",
    "permalink": "/docs/KnowledgeBase/Branding-guide"
  },
  "next": {
    "title": "Network Protocol",
    "permalink": "/docs/Protocol/Network-Protocol"
  }
}